{"document_docker_port_mapping.md":"74f8b79a","document_typescript_keyword-keyof.md":"368fccbb","document_docker_add_copy.md":"9cab258a","document_javascript_index.md":"bd014743","document_vue_render_readme.md":"f1b17435","document_docker_readme.md":"96b75055","document_css_gird.md":"7a60bec3","document_javascript_cropper.md":"3e068f67","document_typescript_readme.md":"b0fc76e0","document_typescript_conditional-types.md":"67456520","document_ubuntu_index.md":"6f2a5369","document_javascript_weakmap.md":"7e20ebdd","document_typescript_namespace.md":"fa01f459","document_vue_render_observer.md":"99263a27","document_typescript_intersections.md":"3a845787","document_typescript_data-type.md":"4221b63c","document_index.md":"47831b9c","document_typescript_keyword-is.md":"682b2d42","document_vue_render_essence-of-comp.md":"4074b840","document_docker_cmd.md":"33c07091","document_typescript_symbol.iterator.md":"286b3846","document_ubuntu_puppeteer.md":"1d466ccf","document_typescript_new-normal-function.md":"cfe616fc","document_typescript_infer.md":"3e6f5dd5","document_ubuntu_proxy.md":"67176228","document_vue_v3_defineproperty.md":"396faac2","document_vue_v3_readme.md":"7737f794","document_typescript_exclamation.md":"b88b6652","document_typescript_discrominated-union.md":"2460883c","document_javascript_proxy.md":"99194ce9","document_vue_v2_recursion.md":"f0ea33b1","document_vue_v3_weakmap-weakset.md":"42dd1e3e","document_typescript_keyword-typeof.md":"7c045318","document_vue_v2_element-ui.md":"e9849d57","document_vue_v2_readme.md":"8b937d67","document_vue_v3_proxy-reflect.md":"766edd7e","zdz_index.md":"0c327767","document_windows_proxy.md":"7f5f5d63","document_vue_render_component-expand.md":"156e6238","document_vue_render_vnode.md":"b8bacfdd","document_vue_v3_scheduler.md":"207aec9f","document_vue_v3_map.md":"92d79f32","document_javascript_proxy-receiver.md":"5283580e","document_windows_index.md":"52aeb3c5","document_vue_v3_set.md":"57ab28aa","index.md":"1cb13e2f","document_vue_v3_vue3.md":"a17eb745","document_vue_v3_shared.md":"dbad3df9","document_vue_v3_inheritattrs.md":"7d18a171","document_vue_render_h.md":"4d92437d","document_vue_v3_event-loop.md":"6f5bf3fc","document_vue_v2_longpress.md":"6663d806","document_vue_render_renderer-advanced.md":"24b13889","document_vue_v3_symbol.md":"58b57d20","document_vue_render_stateful-component.md":"bd224039","document_typescript_challenges_easy.md":"766dc6c3","document_vue_render_renderer.md":"fd4428b0","document_vue_render_renderer-diff.md":"606e0f4b","document_vue_render_renderer-patch.md":"bfeec4e9","document_vue_v3_observer.md":"a308cf8a"}
